korea_public_data/__init__.py
korea_public_data/core/__init__.py
korea_public_data/core/choices.py
korea_public_data/core/consts/__init__.py
korea_public_data/core/consts/data.py
korea_public_data/core/utils/__init__.py
korea_public_data/core/utils/convert.py
korea_public_data/core/utils/hangul_utils.py
korea_public_data/core/vars/__init__.py
korea_public_data/core/vars/default.py
korea_public_data/data/__init__.py
korea_public_data/data/base.py
korea_public_data/data/data_go_kr/__init__.py
korea_public_data/data/data_go_kr/apt_trade.py
korea_public_data/data/data_go_kr/apt_trade_detail.py
korea_public_data/data/data_go_kr/covid_infection_status.py
korea_public_data/data/data_go_kr/get_minu_dust_week_frcst_dspth.py
korea_public_data/data/data_go_kr/nts_businessman.py
korea_public_data/data/data_go_kr/so_city_stats.py
korea_public_data/data/data_go_kr/station_by_route.py
korea_public_data/data/kobis_or_kr/__init__.py
korea_public_data/data/kobis_or_kr/search_daily_box_office_list.py
korea_public_data/data/koreaexim_go_kr/__init__.py
korea_public_data/data/koreaexim_go_kr/exchange.py
korea_public_data/service/__init__.py
korea_public_data/service/app.py
korea_public_data/tests/__init__.py
korea_public_data/tests/test_create_id.py
korea_public_data/tests/test_data_go_kr.py
korea_public_data/tests/test_kobis_or_kr.py
korea_public_data/tests/test_koreaxim_go_kr.py
korea_public_data-0.0.5.dist-info/METADATA
korea_public_data-0.0.5.dist-info/WHEEL
korea_public_data-0.0.5.dist-info/top_level.txt
korea_public_data-0.0.5.dist-info/RECORD
