Metadata-Version: 2.1
Name: korea-public-data
Version: 0.0.5
Summary: Korea Public Data
Home-page: https://github.com/ja-y-com/korea-public-data/
Author: JAY
Author-email: root@ja-y.com
License: UNKNOWN
Platform: UNKNOWN
Classifier: Programming Language :: Python :: 3
Classifier: License :: OSI Approved :: MIT License
Classifier: Operating System :: OS Independent
Requires-Python: >=3.7
Requires-Dist: certifi (==2021.10.8)
Requires-Dist: charset-normalizer (==2.0.12)
Requires-Dist: idna (==3.3)
Requires-Dist: pytz (==2022.1)
Requires-Dist: requests (==2.27.1)
Requires-Dist: urllib3 (==1.26.9)
Requires-Dist: xmltodict (==0.12.0)
